{
  "stateId": 3133897,
  "stateCode": "NO-19",
  "countryCode": "NO",
  "cities": [
    {
      "id": 3162091,
      "name": "Balsfjord",
      "nativeName": "Balsfjord",
      "code": "NO-19-3162091",
      "countryId": 3144096,
      "countryCode": "NO",
      "stateCode": "NO-19",
      "latitude": 69.24024,
      "longitude": 19.22653
    },
    {
      "id": 3162043,
      "name": "Bardu",
      "nativeName": "Bardu",
      "code": "NO-19-3162043",
      "countryId": 3144096,
      "countryCode": "NO",
      "stateCode": "NO-19",
      "latitude": 68.86058,
      "longitude": 18.35052
    },
    {
      "id": 3158837,
      "name": "Dyrøy",
      "nativeName": "Dyrøy",
      "code": "NO-19-3158837",
      "countryId": 3144096,
      "countryCode": "NO",
      "stateCode": "NO-19",
      "latitude": 69.09154,
      "longitude": 17.69094
    },
    {
      "id": 3155195,
      "name": "Gratangen",
      "nativeName": "Gratangen",
      "code": "NO-19-3155195",
      "countryId": 3144096,
      "countryCode": "NO",
      "stateCode": "NO-19",
      "latitude": 68.69273,
      "longitude": 17.53186
    },
    {
      "id": 6453319,
      "name": "Harstad",
      "nativeName": "Harstad",
      "code": "NO-19-6453319",
      "countryId": 3144096,
      "countryCode": "NO",
      "stateCode": "NO-19",
      "latitude": 68.79896,
      "longitude": 16.5293
    },
    {
      "id": 3151230,
      "name": "Ibestad",
      "nativeName": "Ibestad",
      "code": "NO-19-3151230",
      "countryId": 3144096,
      "countryCode": "NO",
      "stateCode": "NO-19",
      "latitude": 68.77866,
      "longitude": 17.17661
    },
    {
      "id": 779339,
      "name": "Karlsøy",
      "nativeName": "Karlsøy",
      "code": "NO-19-779339",
      "countryId": 3144096,
      "countryCode": "NO",
      "stateCode": "NO-19",
      "latitude": 69.96185,
      "longitude": 19.61811
    },
    {
      "id": 3149109,
      "name": "Kvæfjord",
      "nativeName": "Kvæfjord",
      "code": "NO-19-3149109",
      "countryId": 3144096,
      "countryCode": "NO",
      "stateCode": "NO-19",
      "latitude": 68.77201,
      "longitude": 16.17294
    },
    {
      "id": 779159,
      "name": "Kvænangen",
      "nativeName": "Kvænangen",
      "code": "NO-19-779159",
      "countryId": 3144096,
      "countryCode": "NO",
      "stateCode": "NO-19",
      "latitude": 69.9389,
      "longitude": 22.04935
    },
    {
      "id": 779367,
      "name": "Kåfjord",
      "nativeName": "Kåfjord",
      "code": "NO-19-779367",
      "countryId": 3144096,
      "countryCode": "NO",
      "stateCode": "NO-19",
      "latitude": 69.604,
      "longitude": 20.53456
    },
    {
      "id": 3147989,
      "name": "Lavangen",
      "nativeName": "Lavangen",
      "code": "NO-19-3147989",
      "countryId": 3144096,
      "countryCode": "NO",
      "stateCode": "NO-19",
      "latitude": 68.74722,
      "longitude": 17.80558
    },
    {
      "id": 778840,
      "name": "Lyngen",
      "nativeName": "Lyngen",
      "code": "NO-19-778840",
      "countryId": 3144096,
      "countryCode": "NO",
      "stateCode": "NO-19",
      "latitude": 69.57621,
      "longitude": 20.21702
    },
    {
      "id": 3146478,
      "name": "Målselv",
      "nativeName": "Målselv",
      "code": "NO-19-3146478",
      "countryId": 3144096,
      "countryCode": "NO",
      "stateCode": "NO-19",
      "latitude": 69.12389,
      "longitude": 18.61498
    },
    {
      "id": 778430,
      "name": "Nordreisa",
      "nativeName": "Nordreisa",
      "code": "NO-19-778430",
      "countryId": 3144096,
      "countryCode": "NO",
      "stateCode": "NO-19",
      "latitude": 69.76825,
      "longitude": 21.02569
    },
    {
      "id": 3140541,
      "name": "Salangen",
      "nativeName": "Salangen",
      "code": "NO-19-3140541",
      "countryId": 3144096,
      "countryCode": "NO",
      "stateCode": "NO-19",
      "latitude": 68.87669,
      "longitude": 17.83375
    },
    {
      "id": 12110627,
      "name": "Senja",
      "nativeName": "Senja",
      "code": "NO-19-12110627",
      "countryId": 3144096,
      "countryCode": "NO",
      "stateCode": "NO-19",
      "latitude": 69.31549,
      "longitude": 17.61353
    },
    {
      "id": 777680,
      "name": "Skjervøy",
      "nativeName": "Skjervøy",
      "code": "NO-19-777680",
      "countryId": 3144096,
      "countryCode": "NO",
      "stateCode": "NO-19",
      "latitude": 70.03379,
      "longitude": 20.97365
    },
    {
      "id": 777394,
      "name": "Storfjord",
      "nativeName": "Storfjord",
      "code": "NO-19-777394",
      "countryId": 3144096,
      "countryCode": "NO",
      "stateCode": "NO-19",
      "latitude": 69.2686,
      "longitude": 19.96089
    },
    {
      "id": 3137432,
      "name": "Sørreisa",
      "nativeName": "Sørreisa",
      "code": "NO-19-3137432",
      "countryId": 3144096,
      "countryCode": "NO",
      "stateCode": "NO-19",
      "latitude": 69.14697,
      "longitude": 18.15629
    },
    {
      "id": 3134549,
      "name": "Tjeldsund",
      "nativeName": "Tjeldsund",
      "code": "NO-19-3134549",
      "countryId": 3144096,
      "countryCode": "NO",
      "stateCode": "NO-19",
      "latitude": 68.55557,
      "longitude": 16.36172
    },
    {
      "id": 6453316,
      "name": "Tromsø",
      "nativeName": "Tromsø",
      "code": "NO-19-6453316",
      "countryId": 3144096,
      "countryCode": "NO",
      "stateCode": "NO-19",
      "latitude": 69.64961,
      "longitude": 18.95702
    }
  ]
}