{
  "stateId": 617483,
  "stateCode": "MD-RI",
  "countryCode": "MD",
  "cities": [
    {
      "id": 617482,
      "name": "Rîşcani",
      "nativeName": "Rîşcani",
      "code": "MD-RI-617482",
      "countryId": 617790,
      "countryCode": "MD",
      "stateCode": "MD-RI",
      "latitude": 47.94792,
      "longitude": 27.56376
    },
    {
      "id": 824102,
      "name": "Alexăndreşti",
      "nativeName": "Alexăndreşti",
      "code": "MD-RI-824102",
      "countryId": 617790,
      "countryCode": "MD",
      "stateCode": "MD-RI",
      "latitude": 47.89398,
      "longitude": 27.43201
    },
    {
      "id": 618640,
      "name": "Aluniş",
      "nativeName": "Aluniş",
      "code": "MD-RI-618640",
      "countryId": 617790,
      "countryCode": "MD",
      "stateCode": "MD-RI",
      "latitude": 47.84704,
      "longitude": 27.65408
    },
    {
      "id": 863762,
      "name": "Armanca",
      "nativeName": "Armanca",
      "code": "MD-RI-863762",
      "countryId": 617790,
      "countryCode": "MD",
      "stateCode": "MD-RI",
      "latitude": 47.98602,
      "longitude": 27.52514
    },
    {
      "id": 618628,
      "name": "Avrămeni",
      "nativeName": "Avrămeni",
      "code": "MD-RI-618628",
      "countryId": 617790,
      "countryCode": "MD",
      "stateCode": "MD-RI",
      "latitude": 47.7851,
      "longitude": 27.26585
    },
    {
      "id": 617697,
      "name": "Borosenii Noi",
      "nativeName": "Borosenii Noi",
      "code": "MD-RI-617697",
      "countryId": 617790,
      "countryCode": "MD",
      "stateCode": "MD-RI",
      "latitude": 47.98863,
      "longitude": 27.47267
    },
    {
      "id": 618521,
      "name": "Branişte",
      "nativeName": "Branişte",
      "code": "MD-RI-618521",
      "countryId": 617790,
      "countryCode": "MD",
      "stateCode": "MD-RI",
      "latitude": 47.79827,
      "longitude": 27.25296
    },
    {
      "id": 618483,
      "name": "Bulhac",
      "nativeName": "Bulhac",
      "code": "MD-RI-618483",
      "countryId": 617790,
      "countryCode": "MD",
      "stateCode": "MD-RI",
      "latitude": 47.92281,
      "longitude": 27.67453
    },
    {
      "id": 618470,
      "name": "Buteşti",
      "nativeName": "Buteşti",
      "code": "MD-RI-618470",
      "countryId": 617790,
      "countryCode": "MD",
      "stateCode": "MD-RI",
      "latitude": 47.79685,
      "longitude": 27.33316
    },
    {
      "id": 829852,
      "name": "Bălanu Nou",
      "nativeName": "Bălanu Nou",
      "code": "MD-RI-829852",
      "countryId": 617790,
      "countryCode": "MD",
      "stateCode": "MD-RI",
      "latitude": 47.96116,
      "longitude": 27.50147
    },
    {
      "id": 618150,
      "name": "Camenca",
      "nativeName": "Camenca",
      "code": "MD-RI-618150",
      "countryId": 617790,
      "countryCode": "MD",
      "stateCode": "MD-RI",
      "latitude": 47.82683,
      "longitude": 27.36262
    },
    {
      "id": 618147,
      "name": "Camencuţa",
      "nativeName": "Camencuţa",
      "code": "MD-RI-618147",
      "countryId": 617790,
      "countryCode": "MD",
      "stateCode": "MD-RI",
      "latitude": 47.83626,
      "longitude": 27.44948
    },
    {
      "id": 829548,
      "name": "Caraiman",
      "nativeName": "Caraiman",
      "code": "MD-RI-829548",
      "countryId": 617790,
      "countryCode": "MD",
      "stateCode": "MD-RI",
      "latitude": 48.1081,
      "longitude": 27.56384
    },
    {
      "id": 618442,
      "name": "Cepăria",
      "nativeName": "Cepăria",
      "code": "MD-RI-618442",
      "countryId": 617790,
      "countryCode": "MD",
      "stateCode": "MD-RI",
      "latitude": 47.93236,
      "longitude": 27.71511
    },
    {
      "id": 829855,
      "name": "Ciobanovca",
      "nativeName": "Ciobanovca",
      "code": "MD-RI-829855",
      "countryId": 617790,
      "countryCode": "MD",
      "stateCode": "MD-RI",
      "latitude": 47.8909,
      "longitude": 27.75782
    },
    {
      "id": 618060,
      "name": "Cobani",
      "nativeName": "Cobani",
      "code": "MD-RI-618060",
      "countryId": 617790,
      "countryCode": "MD",
      "stateCode": "MD-RI",
      "latitude": 47.76718,
      "longitude": 27.32195
    },
    {
      "id": 618031,
      "name": "Copăceanca",
      "nativeName": "Copăceanca",
      "code": "MD-RI-618031",
      "countryId": 617790,
      "countryCode": "MD",
      "stateCode": "MD-RI",
      "latitude": 47.96694,
      "longitude": 27.55056
    },
    {
      "id": 617873,
      "name": "Corlăteni",
      "nativeName": "Corlăteni",
      "code": "MD-RI-617873",
      "countryId": 617790,
      "countryCode": "MD",
      "stateCode": "MD-RI",
      "latitude": 47.82862,
      "longitude": 27.8447
    },
    {
      "id": 618000,
      "name": "Costeşti",
      "nativeName": "Costeşti",
      "code": "MD-RI-618000",
      "countryId": 617790,
      "countryCode": "MD",
      "stateCode": "MD-RI",
      "latitude": 47.85791,
      "longitude": 27.25947
    },
    {
      "id": 617681,
      "name": "Cucuieţii Noi",
      "nativeName": "Cucuieţii Noi",
      "code": "MD-RI-617681",
      "countryId": 617790,
      "countryCode": "MD",
      "stateCode": "MD-RI",
      "latitude": 47.89296,
      "longitude": 27.41923
    },
    {
      "id": 617331,
      "name": "Cucuieţii Vechi",
      "nativeName": "Cucuieţii Vechi",
      "code": "MD-RI-617331",
      "countryId": 617790,
      "countryCode": "MD",
      "stateCode": "MD-RI",
      "latitude": 47.90782,
      "longitude": 27.43264
    },
    {
      "id": 617738,
      "name": "Dobrogea Nouă",
      "nativeName": "Dobrogea Nouă",
      "code": "MD-RI-617738",
      "countryId": 617790,
      "countryCode": "MD",
      "stateCode": "MD-RI",
      "latitude": 47.82943,
      "longitude": 27.94409
    },
    {
      "id": 617355,
      "name": "Dobrogea Veche",
      "nativeName": "Dobrogea Veche",
      "code": "MD-RI-617355",
      "countryId": 617790,
      "countryCode": "MD",
      "stateCode": "MD-RI",
      "latitude": 47.84029,
      "longitude": 27.93285
    },
    {
      "id": 829530,
      "name": "Druţa",
      "nativeName": "Druţa",
      "code": "MD-RI-829530",
      "countryId": 617790,
      "countryCode": "MD",
      "stateCode": "MD-RI",
      "latitude": 47.96542,
      "longitude": 27.29705
    },
    {
      "id": 618357,
      "name": "Dumeni",
      "nativeName": "Dumeni",
      "code": "MD-RI-618357",
      "countryId": 617790,
      "countryCode": "MD",
      "stateCode": "MD-RI",
      "latitude": 47.91113,
      "longitude": 27.20271
    },
    {
      "id": 618355,
      "name": "Duruitoarea",
      "nativeName": "Duruitoarea",
      "code": "MD-RI-618355",
      "countryId": 617790,
      "countryCode": "MD",
      "stateCode": "MD-RI",
      "latitude": 47.87719,
      "longitude": 27.26069
    },
    {
      "id": 617692,
      "name": "Duruitoarea Nouă",
      "nativeName": "Duruitoarea Nouă",
      "code": "MD-RI-617692",
      "countryId": 617790,
      "countryCode": "MD",
      "stateCode": "MD-RI",
      "latitude": 47.89614,
      "longitude": 27.24561
    },
    {
      "id": 829846,
      "name": "Dămăşcani",
      "nativeName": "Dămăşcani",
      "code": "MD-RI-829846",
      "countryId": 617790,
      "countryCode": "MD",
      "stateCode": "MD-RI",
      "latitude": 47.86769,
      "longitude": 27.305
    },
    {
      "id": 618227,
      "name": "Grinăuţi",
      "nativeName": "Grinăuţi",
      "code": "MD-RI-618227",
      "countryId": 617790,
      "countryCode": "MD",
      "stateCode": "MD-RI",
      "latitude": 47.88177,
      "longitude": 27.78177
    },
    {
      "id": 618311,
      "name": "Gălăşeni",
      "nativeName": "Gălăşeni",
      "code": "MD-RI-618311",
      "countryId": 617790,
      "countryCode": "MD",
      "stateCode": "MD-RI",
      "latitude": 47.87098,
      "longitude": 27.34053
    },
    {
      "id": 618098,
      "name": "Hiliuţi",
      "nativeName": "Hiliuţi",
      "code": "MD-RI-618098",
      "countryId": 617790,
      "countryCode": "MD",
      "stateCode": "MD-RI",
      "latitude": 47.93007,
      "longitude": 27.38926
    },
    {
      "id": 618247,
      "name": "Horodişte",
      "nativeName": "Horodişte",
      "code": "MD-RI-618247",
      "countryId": 617790,
      "countryCode": "MD",
      "stateCode": "MD-RI",
      "latitude": 47.95369,
      "longitude": 27.26303
    },
    {
      "id": 617701,
      "name": "Hăsnăşenii Noi",
      "nativeName": "Hăsnăşenii Noi",
      "code": "MD-RI-617701",
      "countryId": 617790,
      "countryCode": "MD",
      "stateCode": "MD-RI",
      "latitude": 47.85513,
      "longitude": 27.90705
    },
    {
      "id": 863759,
      "name": "Ivăneşti",
      "nativeName": "Ivăneşti",
      "code": "MD-RI-863759",
      "countryId": 617790,
      "countryCode": "MD",
      "stateCode": "MD-RI",
      "latitude": 47.88778,
      "longitude": 27.41722
    },
    {
      "id": 617874,
      "name": "Lupăria",
      "nativeName": "Lupăria",
      "code": "MD-RI-617874",
      "countryId": 617790,
      "countryCode": "MD",
      "stateCode": "MD-RI",
      "latitude": 47.87793,
      "longitude": 27.55428
    },
    {
      "id": 617858,
      "name": "Malinovscoe",
      "nativeName": "Malinovscoe",
      "code": "MD-RI-617858",
      "countryId": 617790,
      "countryCode": "MD",
      "stateCode": "MD-RI",
      "latitude": 47.88445,
      "longitude": 27.50647
    },
    {
      "id": 617807,
      "name": "Mihăileni",
      "nativeName": "Mihăileni",
      "code": "MD-RI-617807",
      "countryId": 617790,
      "countryCode": "MD",
      "stateCode": "MD-RI",
      "latitude": 48.04017,
      "longitude": 27.61681
    },
    {
      "id": 829546,
      "name": "Mihăilenii Noi",
      "nativeName": "Mihăilenii Noi",
      "code": "MD-RI-829546",
      "countryId": 617790,
      "countryCode": "MD",
      "stateCode": "MD-RI",
      "latitude": 48.03341,
      "longitude": 27.53413
    },
    {
      "id": 617786,
      "name": "Moşeni",
      "nativeName": "Moşeni",
      "code": "MD-RI-617786",
      "countryId": 617790,
      "countryCode": "MD",
      "stateCode": "MD-RI",
      "latitude": 48.02861,
      "longitude": 27.45501
    },
    {
      "id": 617860,
      "name": "Mălăieşti",
      "nativeName": "Mălăieşti",
      "code": "MD-RI-617860",
      "countryId": 617790,
      "countryCode": "MD",
      "stateCode": "MD-RI",
      "latitude": 47.88468,
      "longitude": 27.34719
    },
    {
      "id": 863763,
      "name": "Nihoreni",
      "nativeName": "Nihoreni",
      "code": "MD-RI-863763",
      "countryId": 617790,
      "countryCode": "MD",
      "stateCode": "MD-RI",
      "latitude": 47.93556,
      "longitude": 27.56194
    },
    {
      "id": 617650,
      "name": "Ochiul Alb",
      "nativeName": "Ochiul Alb",
      "code": "MD-RI-617650",
      "countryId": 617790,
      "countryCode": "MD",
      "stateCode": "MD-RI",
      "latitude": 48.01847,
      "longitude": 27.67184
    },
    {
      "id": 617614,
      "name": "Pelinia",
      "nativeName": "Pelinia",
      "code": "MD-RI-617614",
      "countryId": 617790,
      "countryCode": "MD",
      "stateCode": "MD-RI",
      "latitude": 47.87589,
      "longitude": 27.83163
    },
    {
      "id": 617592,
      "name": "Petruşeni",
      "nativeName": "Petruşeni",
      "code": "MD-RI-617592",
      "countryId": 617790,
      "countryCode": "MD",
      "stateCode": "MD-RI",
      "latitude": 47.84828,
      "longitude": 27.31216
    },
    {
      "id": 618367,
      "name": "Pociumbeni",
      "nativeName": "Pociumbeni",
      "code": "MD-RI-618367",
      "countryId": 617790,
      "countryCode": "MD",
      "stateCode": "MD-RI",
      "latitude": 47.97799,
      "longitude": 27.30432
    },
    {
      "id": 617580,
      "name": "Pociumbăuţi",
      "nativeName": "Pociumbăuţi",
      "code": "MD-RI-617580",
      "countryId": 617790,
      "countryCode": "MD",
      "stateCode": "MD-RI",
      "latitude": 47.99723,
      "longitude": 27.32185
    },
    {
      "id": 617548,
      "name": "Proscureni",
      "nativeName": "Proscureni",
      "code": "MD-RI-617548",
      "countryId": 617790,
      "countryCode": "MD",
      "stateCode": "MD-RI",
      "latitude": 47.86241,
      "longitude": 27.25848
    },
    {
      "id": 617532,
      "name": "Pîrjota",
      "nativeName": "Pîrjota",
      "code": "MD-RI-617532",
      "countryId": 617790,
      "countryCode": "MD",
      "stateCode": "MD-RI",
      "latitude": 47.95668,
      "longitude": 27.43104
    },
    {
      "id": 617620,
      "name": "Păscăuţi",
      "nativeName": "Păscăuţi",
      "code": "MD-RI-617620",
      "countryId": 617790,
      "countryCode": "MD",
      "stateCode": "MD-RI",
      "latitude": 47.83496,
      "longitude": 27.27869
    },
    {
      "id": 617520,
      "name": "Recea",
      "nativeName": "Recea",
      "code": "MD-RI-617520",
      "countryId": 617790,
      "countryCode": "MD",
      "stateCode": "MD-RI",
      "latitude": 47.89429,
      "longitude": 27.67117
    },
    {
      "id": 829849,
      "name": "Reteni",
      "nativeName": "Reteni",
      "code": "MD-RI-829849",
      "countryId": 617790,
      "countryCode": "MD",
      "stateCode": "MD-RI",
      "latitude": 47.81138,
      "longitude": 27.25458
    },
    {
      "id": 829850,
      "name": "Reteni-Vasileuţi",
      "nativeName": "Reteni-Vasileuţi",
      "code": "MD-RI-829850",
      "countryId": 617790,
      "countryCode": "MD",
      "stateCode": "MD-RI",
      "latitude": 47.80756,
      "longitude": 27.26045
    },
    {
      "id": 617530,
      "name": "Răcăria",
      "nativeName": "Răcăria",
      "code": "MD-RI-617530",
      "countryId": 617790,
      "countryCode": "MD",
      "stateCode": "MD-RI",
      "latitude": 47.9105,
      "longitude": 27.61335
    },
    {
      "id": 617527,
      "name": "Rămăzan",
      "nativeName": "Rămăzan",
      "code": "MD-RI-617527",
      "countryId": 617790,
      "countryCode": "MD",
      "stateCode": "MD-RI",
      "latitude": 47.98613,
      "longitude": 27.61571
    },
    {
      "id": 617280,
      "name": "Singureni",
      "nativeName": "Singureni",
      "code": "MD-RI-617280",
      "countryId": 617790,
      "countryCode": "MD",
      "stateCode": "MD-RI",
      "latitude": 47.82417,
      "longitude": 27.85444
    },
    {
      "id": 829854,
      "name": "Slobozia-Recea",
      "nativeName": "Slobozia-Recea",
      "code": "MD-RI-829854",
      "countryId": 617790,
      "countryCode": "MD",
      "stateCode": "MD-RI",
      "latitude": 47.85379,
      "longitude": 27.69933
    },
    {
      "id": 617298,
      "name": "Sturzeni",
      "nativeName": "Sturzeni",
      "code": "MD-RI-617298",
      "countryId": 617790,
      "countryCode": "MD",
      "stateCode": "MD-RI",
      "latitude": 47.9171,
      "longitude": 27.46133
    },
    {
      "id": 617282,
      "name": "Sverdiac",
      "nativeName": "Sverdiac",
      "code": "MD-RI-617282",
      "countryId": 617790,
      "countryCode": "MD",
      "stateCode": "MD-RI",
      "latitude": 47.89575,
      "longitude": 27.72842
    },
    {
      "id": 617172,
      "name": "Uşurei",
      "nativeName": "Uşurei",
      "code": "MD-RI-617172",
      "countryId": 617790,
      "countryCode": "MD",
      "stateCode": "MD-RI",
      "latitude": 47.8919,
      "longitude": 27.59438
    },
    {
      "id": 617144,
      "name": "Vasileuţi",
      "nativeName": "Vasileuţi",
      "code": "MD-RI-617144",
      "countryId": 617790,
      "countryCode": "MD",
      "stateCode": "MD-RI",
      "latitude": 48.00748,
      "longitude": 27.51175
    },
    {
      "id": 617150,
      "name": "Văratic",
      "nativeName": "Văratic",
      "code": "MD-RI-617150",
      "countryId": 617790,
      "countryCode": "MD",
      "stateCode": "MD-RI",
      "latitude": 47.9172,
      "longitude": 27.26067
    },
    {
      "id": 617049,
      "name": "Zăicani",
      "nativeName": "Zăicani",
      "code": "MD-RI-617049",
      "countryId": 617790,
      "countryCode": "MD",
      "stateCode": "MD-RI",
      "latitude": 47.97604,
      "longitude": 27.36898
    },
    {
      "id": 617430,
      "name": "Şaptebani",
      "nativeName": "Şaptebani",
      "code": "MD-RI-617430",
      "countryId": 617790,
      "countryCode": "MD",
      "stateCode": "MD-RI",
      "latitude": 47.89939,
      "longitude": 27.3472
    },
    {
      "id": 617412,
      "name": "Ştiubeieni",
      "nativeName": "Ştiubeieni",
      "code": "MD-RI-617412",
      "countryId": 617790,
      "countryCode": "MD",
      "stateCode": "MD-RI",
      "latitude": 48.03095,
      "longitude": 27.51452
    },
    {
      "id": 617411,
      "name": "Şumna",
      "nativeName": "Şumna",
      "code": "MD-RI-617411",
      "countryId": 617790,
      "countryCode": "MD",
      "stateCode": "MD-RI",
      "latitude": 47.92131,
      "longitude": 27.70595
    }
  ]
}