{
  "stateId": 2044245,
  "stateCode": "KP-09",
  "countryCode": "KP",
  "cities": [
    {
      "id": 2044754,
      "name": "Ch’ŏngjin-si",
      "nativeName": "Ch’ŏngjin-si",
      "code": "KP-09-2044754",
      "countryId": 1873107,
      "countryCode": "KP",
      "stateCode": "KP-09",
      "latitude": 41.88722,
      "longitude": 129.83194
    },
    {
      "id": 2044094,
      "name": "Hoeryŏng",
      "nativeName": "Hoeryŏng",
      "code": "KP-09-2044094",
      "countryId": 1873107,
      "countryCode": "KP",
      "stateCode": "KP-09",
      "latitude": 42.41261,
      "longitude": 129.82646
    },
    {
      "id": 2043963,
      "name": "Hwadae-gun",
      "nativeName": "Hwadae-gun",
      "code": "KP-09-2043963",
      "countryId": 1873107,
      "countryCode": "KP",
      "stateCode": "KP-09",
      "latitude": 40.83256,
      "longitude": 129.49393
    },
    {
      "id": 2043486,
      "name": "Kilchu-gun",
      "nativeName": "Kilchu-gun",
      "code": "KP-09-2043486",
      "countryId": 1873107,
      "countryCode": "KP",
      "stateCode": "KP-09",
      "latitude": 41,
      "longitude": 129.16667
    },
    {
      "id": 2043476,
      "name": "Kimch’aek-si",
      "nativeName": "Kimch’aek-si",
      "code": "KP-09-2043476",
      "countryId": 1873107,
      "countryCode": "KP",
      "stateCode": "KP-09",
      "latitude": 40.77429,
      "longitude": 129.12553
    },
    {
      "id": 2039588,
      "name": "Kyŏnghŭng",
      "nativeName": "Kyŏnghŭng",
      "code": "KP-09-2039588",
      "countryId": 1873107,
      "countryCode": "KP",
      "stateCode": "KP-09",
      "latitude": 42.4715,
      "longitude": 130.19721
    },
    {
      "id": 2042989,
      "name": "Kyŏngsŏng-gun",
      "nativeName": "Kyŏngsŏng-gun",
      "code": "KP-09-2042989",
      "countryId": 1873107,
      "countryCode": "KP",
      "stateCode": "KP-09",
      "latitude": 41.68496,
      "longitude": 129.45309
    },
    {
      "id": 2041593,
      "name": "Kyŏngwŏn",
      "nativeName": "Kyŏngwŏn",
      "code": "KP-09-2041593",
      "countryId": 1873107,
      "countryCode": "KP",
      "stateCode": "KP-09",
      "latitude": 42.74534,
      "longitude": 130.14884
    },
    {
      "id": 2042740,
      "name": "Musan-gun",
      "nativeName": "Musan-gun",
      "code": "KP-09-2042740",
      "countryId": 1873107,
      "countryCode": "KP",
      "stateCode": "KP-09",
      "latitude": 42.13034,
      "longitude": 129.33546
    },
    {
      "id": 2042719,
      "name": "Myŏngch’ŏn-gun",
      "nativeName": "Myŏngch’ŏn-gun",
      "code": "KP-09-2042719",
      "countryId": 1873107,
      "countryCode": "KP",
      "stateCode": "KP-09",
      "latitude": 40.97028,
      "longitude": 129.48444
    },
    {
      "id": 2042710,
      "name": "Myŏnggan-gun",
      "nativeName": "Myŏnggan-gun",
      "code": "KP-09-2042710",
      "countryId": 1873107,
      "countryCode": "KP",
      "stateCode": "KP-09",
      "latitude": 41.14067,
      "longitude": 129.43206
    },
    {
      "id": 2042268,
      "name": "Onsŏng-gun",
      "nativeName": "Onsŏng-gun",
      "code": "KP-09-2042268",
      "countryId": 1873107,
      "countryCode": "KP",
      "stateCode": "KP-09",
      "latitude": 42.8701,
      "longitude": 129.97957
    },
    {
      "id": 2041700,
      "name": "Puryŏng-gun",
      "nativeName": "Puryŏng-gun",
      "code": "KP-09-2041700",
      "countryId": 1873107,
      "countryCode": "KP",
      "stateCode": "KP-09",
      "latitude": 42.11689,
      "longitude": 129.69258
    },
    {
      "id": 2038910,
      "name": "Yŏnsa-gun",
      "nativeName": "Yŏnsa-gun",
      "code": "KP-09-2038910",
      "countryId": 1873107,
      "countryCode": "KP",
      "stateCode": "KP-09",
      "latitude": 41.79694,
      "longitude": 129.09139
    },
    {
      "id": 2042256,
      "name": "Ŏrang-gun",
      "nativeName": "Ŏrang-gun",
      "code": "KP-09-2042256",
      "countryId": 1873107,
      "countryCode": "KP",
      "stateCode": "KP-09",
      "latitude": 41.39644,
      "longitude": 129.36946
    }
  ]
}