{
  "stateId": 3575179,
  "stateCode": "KN-04",
  "countryCode": "KN",
  "cities": [
    {
      "id": 3575296,
      "name": "Market Shop",
      "nativeName": "Market Shop",
      "code": "KN-04-3575296",
      "countryId": 3575174,
      "countryCode": "KN",
      "stateCode": "KN-04",
      "latitude": 17.13218,
      "longitude": -62.57267
    },
    {
      "id": 3575558,
      "name": "Bachelors Hall",
      "nativeName": "Bachelors Hall",
      "code": "KN-04-3575558",
      "countryId": 3575174,
      "countryCode": "KN",
      "stateCode": "KN-04",
      "latitude": 17.13333,
      "longitude": -62.51667
    },
    {
      "id": 3575512,
      "name": "Buck’s Hill",
      "nativeName": "Buck’s Hill",
      "code": "KN-04-3575512",
      "countryId": 3575174,
      "countryCode": "KN",
      "stateCode": "KN-04",
      "latitude": 17.12625,
      "longitude": -62.56403
    },
    {
      "id": 3575478,
      "name": "Chicken Stone",
      "nativeName": "Chicken Stone",
      "code": "KN-04-3575478",
      "countryId": 3575174,
      "countryCode": "KN",
      "stateCode": "KN-04",
      "latitude": 17.13178,
      "longitude": -62.57963
    },
    {
      "id": 3575448,
      "name": "Crook’s Ground",
      "nativeName": "Crook’s Ground",
      "code": "KN-04-3575448",
      "countryId": 3575174,
      "countryCode": "KN",
      "stateCode": "KN-04",
      "latitude": 17.12875,
      "longitude": -62.56793
    },
    {
      "id": 3575424,
      "name": "Fenton Hill",
      "nativeName": "Fenton Hill",
      "code": "KN-04-3575424",
      "countryId": 3575174,
      "countryCode": "KN",
      "stateCode": "KN-04",
      "latitude": 17.13895,
      "longitude": -62.56486
    },
    {
      "id": 3575419,
      "name": "Fothergill",
      "nativeName": "Fothergill",
      "code": "KN-04-3575419",
      "countryId": 3575174,
      "countryCode": "KN",
      "stateCode": "KN-04",
      "latitude": 17.15,
      "longitude": -62.55
    },
    {
      "id": 3575403,
      "name": "Gingerland",
      "nativeName": "Gingerland",
      "code": "KN-04-3575403",
      "countryId": 3575174,
      "countryCode": "KN",
      "stateCode": "KN-04",
      "latitude": 17.13517,
      "longitude": -62.56928
    },
    {
      "id": 3575380,
      "name": "Hardtimes",
      "nativeName": "Hardtimes",
      "code": "KN-04-3575380",
      "countryId": 3575174,
      "countryCode": "KN",
      "stateCode": "KN-04",
      "latitude": 17.13333,
      "longitude": -62.55
    },
    {
      "id": 3575377,
      "name": "Harris",
      "nativeName": "Harris",
      "code": "KN-04-3575377",
      "countryId": 3575174,
      "countryCode": "KN",
      "stateCode": "KN-04",
      "latitude": 17.1463,
      "longitude": -62.55874
    },
    {
      "id": 3575366,
      "name": "Hermitage",
      "nativeName": "Hermitage",
      "code": "KN-04-3575366",
      "countryId": 3575174,
      "countryCode": "KN",
      "stateCode": "KN-04",
      "latitude": 17.13289,
      "longitude": -62.58126
    },
    {
      "id": 3575363,
      "name": "Hichmans",
      "nativeName": "Hichmans",
      "code": "KN-04-3575363",
      "countryId": 3575174,
      "countryCode": "KN",
      "stateCode": "KN-04",
      "latitude": 17.13772,
      "longitude": -62.55443
    },
    {
      "id": 3575356,
      "name": "Holmes Hill",
      "nativeName": "Holmes Hill",
      "code": "KN-04-3575356",
      "countryId": 3575174,
      "countryCode": "KN",
      "stateCode": "KN-04",
      "latitude": 17.11919,
      "longitude": -62.55814
    },
    {
      "id": 3575350,
      "name": "Hull Ground",
      "nativeName": "Hull Ground",
      "code": "KN-04-3575350",
      "countryId": 3575174,
      "countryCode": "KN",
      "stateCode": "KN-04",
      "latitude": 17.14137,
      "longitude": -62.57334
    },
    {
      "id": 3575294,
      "name": "Maynards Ground",
      "nativeName": "Maynards Ground",
      "code": "KN-04-3575294",
      "countryId": 3575174,
      "countryCode": "KN",
      "stateCode": "KN-04",
      "latitude": 17.12805,
      "longitude": -62.57247
    },
    {
      "id": 3575257,
      "name": "New River",
      "nativeName": "New River",
      "code": "KN-04-3575257",
      "countryId": 3575174,
      "countryCode": "KN",
      "stateCode": "KN-04",
      "latitude": 17.14526,
      "longitude": -62.55266
    },
    {
      "id": 3575198,
      "name": "Rawlins",
      "nativeName": "Rawlins",
      "code": "KN-04-3575198",
      "countryId": 3575174,
      "countryCode": "KN",
      "stateCode": "KN-04",
      "latitude": 17.14389,
      "longitude": -62.57176
    },
    {
      "id": 3575195,
      "name": "Rices",
      "nativeName": "Rices",
      "code": "KN-04-3575195",
      "countryId": 3575174,
      "countryCode": "KN",
      "stateCode": "KN-04",
      "latitude": 17.12828,
      "longitude": -62.56245
    },
    {
      "id": 3575149,
      "name": "Sherriffs",
      "nativeName": "Sherriffs",
      "code": "KN-04-3575149",
      "countryId": 3575174,
      "countryCode": "KN",
      "stateCode": "KN-04",
      "latitude": 17.12202,
      "longitude": -62.55894
    },
    {
      "id": 3575130,
      "name": "Stonyhill",
      "nativeName": "Stonyhill",
      "code": "KN-04-3575130",
      "countryId": 3575174,
      "countryCode": "KN",
      "stateCode": "KN-04",
      "latitude": 17.14313,
      "longitude": -62.56675
    },
    {
      "id": 3575124,
      "name": "Taylors Pasture",
      "nativeName": "Taylors Pasture",
      "code": "KN-04-3575124",
      "countryId": 3575174,
      "countryCode": "KN",
      "stateCode": "KN-04",
      "latitude": 17.13027,
      "longitude": -62.57459
    },
    {
      "id": 3575099,
      "name": "Webb’s Ground",
      "nativeName": "Webb’s Ground",
      "code": "KN-04-3575099",
      "countryId": 3575174,
      "countryCode": "KN",
      "stateCode": "KN-04",
      "latitude": 17.14516,
      "longitude": -62.56057
    },
    {
      "id": 3575078,
      "name": "Zetlands",
      "nativeName": "Zetlands",
      "code": "KN-04-3575078",
      "countryId": 3575174,
      "countryCode": "KN",
      "stateCode": "KN-04",
      "latitude": 17.13856,
      "longitude": -62.57557
    },
    {
      "id": 3575076,
      "name": "Zion",
      "nativeName": "Zion",
      "code": "KN-04-3575076",
      "countryId": 3575174,
      "countryCode": "KN",
      "stateCode": "KN-04",
      "latitude": 17.14157,
      "longitude": -62.56109
    }
  ]
}