{
  "stateId": 9259067,
  "stateCode": "SB-CT",
  "countryCode": "SB",
  "cities": [
    {
      "id": 12041748,
      "name": "Cruz",
      "nativeName": "Cruz",
      "code": "SB-CT-12041748",
      "countryId": 2103350,
      "countryCode": "SB",
      "stateCode": "SB-CT",
      "latitude": -9.43112,
      "longitude": 159.95447
    },
    {
      "id": 12041803,
      "name": "Kola'A",
      "nativeName": "Kola'A",
      "code": "SB-CT-12041803",
      "countryId": 2103350,
      "countryCode": "SB",
      "stateCode": "SB-CT",
      "latitude": -9.44599,
      "longitude": 159.96982
    },
    {
      "id": 12041751,
      "name": "Kukum",
      "nativeName": "Kukum",
      "code": "SB-CT-12041751",
      "countryId": 2103350,
      "countryCode": "SB",
      "stateCode": "SB-CT",
      "latitude": -9.43497,
      "longitude": 159.97948
    },
    {
      "id": 12041802,
      "name": "Mataniko",
      "nativeName": "Mataniko",
      "code": "SB-CT-12041802",
      "countryId": 2103350,
      "countryCode": "SB",
      "stateCode": "SB-CT",
      "latitude": -9.44554,
      "longitude": 159.95909
    },
    {
      "id": 12041746,
      "name": "Mbumburu",
      "nativeName": "Mbumburu",
      "code": "SB-CT-12041746",
      "countryId": 2103350,
      "countryCode": "SB",
      "stateCode": "SB-CT",
      "latitude": -9.43801,
      "longitude": 159.9443
    },
    {
      "id": 12041752,
      "name": "Naha",
      "nativeName": "Naha",
      "code": "SB-CT-12041752",
      "countryId": 2103350,
      "countryCode": "SB",
      "stateCode": "SB-CT",
      "latitude": -9.43303,
      "longitude": 159.98186
    },
    {
      "id": 12041744,
      "name": "Nggosi",
      "nativeName": "Nggosi",
      "code": "SB-CT-12041744",
      "countryId": 2103350,
      "countryCode": "SB",
      "stateCode": "SB-CT",
      "latitude": -9.43205,
      "longitude": 159.9285
    },
    {
      "id": 12041828,
      "name": "Panatina",
      "nativeName": "Panatina",
      "code": "SB-CT-12041828",
      "countryId": 2103350,
      "countryCode": "SB",
      "stateCode": "SB-CT",
      "latitude": -9.43587,
      "longitude": 159.99591
    },
    {
      "id": 12041747,
      "name": "Rove - Lengakiki",
      "nativeName": "Rove - Lengakiki",
      "code": "SB-CT-12041747",
      "countryId": 2103350,
      "countryCode": "SB",
      "stateCode": "SB-CT",
      "latitude": -9.43164,
      "longitude": 159.94492
    },
    {
      "id": 12041777,
      "name": "Vavaea",
      "nativeName": "Vavaea",
      "code": "SB-CT-12041777",
      "countryId": 2103350,
      "countryCode": "SB",
      "stateCode": "SB-CT",
      "latitude": -9.43496,
      "longitude": 159.95695
    },
    {
      "id": 12041778,
      "name": "Vuhokesa",
      "nativeName": "Vuhokesa",
      "code": "SB-CT-12041778",
      "countryId": 2103350,
      "countryCode": "SB",
      "stateCode": "SB-CT",
      "latitude": -9.43574,
      "longitude": 159.96443
    },
    {
      "id": 12041805,
      "name": "Vura",
      "nativeName": "Vura",
      "code": "SB-CT-12041805",
      "countryId": 2103350,
      "countryCode": "SB",
      "stateCode": "SB-CT",
      "latitude": -9.44432,
      "longitude": 159.98456
    }
  ]
}